{
  "type": "Feature",
  "properties": {
    "gn:admin1_code":"213",
    "gn:admin2_code":"35.0",
    "gn:asciiname":"Notholm",
    "gn:country_code":"AX",
    "gn:dem":-9999,
    "gn:feature_class":"P",
    "gn:feature_code":"PPL",
    "gn:name":"Notholm",
    "gn:population":0,
    "gn:timezone":"Europe/Mariehamn",
    "iso:country":"AX",
    "wof:name":"Notholm",
    "wof:placetype":"locality"
},
  "geometry": {"coordinates":[20.93,60.43666999999999],"type":"Point"}
}