{
  "type": "Feature",
  "properties": {
    "gn:admin1_code":"212",
    "gn:admin2_code":"60.0",
    "gn:asciiname":"Bjoerkbacka",
    "gn:country_code":"AX",
    "gn:dem":6,
    "gn:feature_class":"P",
    "gn:feature_code":"PPL",
    "gn:name":"Bj\u00f6rkbacka",
    "gn:population":0,
    "gn:timezone":"Europe/Mariehamn",
    "iso:country":"AX",
    "wof:name":"Bjoerkbacka",
    "wof:placetype":"locality"
},
  "geometry": {"coordinates":[19.85417,60.21556],"type":"Point"}
}