{
  "type": "Feature",
  "properties": {
    "gn:admin1_code":"213",
    "gn:admin2_code":"295.0",
    "gn:asciiname":"Vaesternaes",
    "gn:country_code":"AX",
    "gn:dem":1,
    "gn:feature_class":"P",
    "gn:feature_code":"PPL",
    "gn:name":"V\u00e4stern\u00e4s",
    "gn:population":0,
    "gn:timezone":"Europe/Mariehamn",
    "iso:country":"AX",
    "wof:name":"Vaesternaes",
    "wof:placetype":"locality"
},
  "geometry": {"coordinates":[20.91861,60.34111],"type":"Point"}
}