{
  "type": "Feature",
  "properties": {
    "gn:admin1_code":"212",
    "gn:admin2_code":"76.0",
    "gn:asciiname":"Moerby",
    "gn:country_code":"AX",
    "gn:dem":7,
    "gn:feature_class":"P",
    "gn:feature_code":"PPL",
    "gn:name":"M\u00f6rby",
    "gn:population":0,
    "gn:timezone":"Europe/Mariehamn",
    "iso:country":"AX",
    "wof:name":"Moerby",
    "wof:placetype":"locality"
},
  "geometry": {"coordinates":[19.71667,60.23333],"type":"Point"}
}