{
  "type": "Feature",
  "properties": {
    "gn:admin1_code":"212",
    "gn:admin2_code":"76.0",
    "gn:asciiname":"Mannes",
    "gn:country_code":"AX",
    "gn:dem":23,
    "gn:feature_class":"P",
    "gn:feature_code":"PPL",
    "gn:name":"Mannes",
    "gn:population":0,
    "gn:timezone":"Europe/Mariehamn",
    "iso:country":"AX",
    "wof:name":"Mannes",
    "wof:placetype":"locality"
},
  "geometry": {"coordinates":[19.74556,60.16833000000001],"type":"Point"}
}