{
  "type": "Feature",
  "properties": {
    "gn:admin1_code":"212",
    "gn:admin2_code":"170.0",
    "gn:asciiname":"Vargsunda",
    "gn:country_code":"AX",
    "gn:dem":11,
    "gn:feature_class":"P",
    "gn:feature_code":"PPL",
    "gn:name":"Vargsunda",
    "gn:population":0,
    "gn:timezone":"Europe/Mariehamn",
    "iso:country":"AX",
    "wof:name":"Vargsunda",
    "wof:placetype":"locality"
},
  "geometry": {"coordinates":[19.85583,60.18028],"type":"Point"}
}