{
  "type": "Feature",
  "properties": {
    "gn:admin1_code":"212",
    "gn:admin2_code":"170.0",
    "gn:asciiname":"Karlberg",
    "gn:country_code":"AX",
    "gn:dem":6,
    "gn:feature_class":"P",
    "gn:feature_code":"PPL",
    "gn:name":"Karlberg",
    "gn:population":0,
    "gn:timezone":"Europe/Mariehamn",
    "iso:country":"AX",
    "wof:name":"Karlberg",
    "wof:placetype":"locality"
},
  "geometry": {"coordinates":[19.81472,60.11221999999999],"type":"Point"}
}