{
  "type": "Feature",
  "properties": {
    "gn:admin1_code":"212",
    "gn:admin2_code":"43.0",
    "gn:asciiname":"Torp",
    "gn:country_code":"AX",
    "gn:dem":16,
    "gn:feature_class":"P",
    "gn:feature_code":"PPL",
    "gn:name":"Torp",
    "gn:population":0,
    "gn:timezone":"Europe/Mariehamn",
    "iso:country":"AX",
    "name:ceb_x_preferred":[
        "Torp"
    ],
    "name:dan_x_preferred":[
        "Torp"
    ],
    "name:deu_x_preferred":[
        "Torp"
    ],
    "name:fra_x_preferred":[
        "Torp"
    ],
    "name:nds_x_preferred":[
        "Torp"
    ],
    "name:nld_x_preferred":[
        "Torp"
    ],
    "name:nor_x_preferred":[
        "Torp"
    ],
    "name:srp_x_preferred":[
        "\u0422\u043e\u0440\u043f"
    ],
    "name:swe_x_preferred":[
        "Torp"
    ],
    "name:und_x_variant":[
        "Torp\u00f6by",
        "Torpby",
        "Torp"
    ],
    "wof:name":"Torp",
    "wof:placetype":"locality"
},
  "geometry": {"coordinates":[19.58333,60.18333000000001],"type":"Point"}
}