{
  "type": "Feature",
  "properties": {
    "gn:admin1_code":"212",
    "gn:admin2_code":"65.0",
    "gn:asciiname":"OEstergeta",
    "gn:country_code":"AX",
    "gn:dem":12,
    "gn:feature_class":"P",
    "gn:feature_code":"PPL",
    "gn:name":"\u00d6stergeta",
    "gn:population":0,
    "gn:timezone":"Europe/Mariehamn",
    "iso:country":"AX",
    "wof:name":"OEstergeta",
    "wof:placetype":"locality"
},
  "geometry": {"coordinates":[19.88333,60.38333000000001],"type":"Point"}
}