{
  "type": "Feature",
  "properties": {
    "gn:admin1_code":"212",
    "gn:admin2_code":"417.0",
    "gn:asciiname":"Nedre Boers",
    "gn:country_code":"AX",
    "gn:dem":8,
    "gn:feature_class":"P",
    "gn:feature_code":"PPL",
    "gn:name":"Nedre B\u00f6rs",
    "gn:population":0,
    "gn:timezone":"Europe/Mariehamn",
    "iso:country":"AX",
    "wof:name":"Nedre Boers",
    "wof:placetype":"locality"
},
  "geometry": {"coordinates":[20.03528,60.07194000000001],"type":"Point"}
}