{
  "type": "Feature",
  "properties": {
    "gn:admin1_code":"213",
    "gn:admin2_code":"295.0",
    "gn:asciiname":"Saelvik",
    "gn:country_code":"AX",
    "gn:dem":-9999,
    "gn:feature_class":"P",
    "gn:feature_code":"PPL",
    "gn:name":"S\u00e4lvik",
    "gn:population":0,
    "gn:timezone":"Europe/Mariehamn",
    "iso:country":"AX",
    "wof:name":"Saelvik",
    "wof:placetype":"locality"
},
  "geometry": {"coordinates":[20.7475,60.35111],"type":"Point"}
}