{
  "type": "Feature",
  "properties": {
    "gn:admin1_code":"212",
    "gn:admin2_code":"60.0",
    "gn:asciiname":"Vikhem",
    "gn:country_code":"AX",
    "gn:dem":6,
    "gn:feature_class":"P",
    "gn:feature_code":"PPL",
    "gn:name":"Vikhem",
    "gn:population":0,
    "gn:timezone":"Europe/Mariehamn",
    "iso:country":"AX",
    "wof:name":"Vikhem",
    "wof:placetype":"locality"
},
  "geometry": {"coordinates":[19.85889,60.20972],"type":"Point"}
}