{
  "type": "Feature",
  "properties": {
    "gn:admin1_code":"212",
    "gn:admin2_code":"736.0",
    "gn:asciiname":"OEdkarby",
    "gn:country_code":"AX",
    "gn:dem":4,
    "gn:feature_class":"P",
    "gn:feature_code":"PPL",
    "gn:name":"\u00d6dkarby",
    "gn:population":0,
    "gn:timezone":"Europe/Mariehamn",
    "iso:country":"AX",
    "wof:name":"OEdkarby",
    "wof:placetype":"locality"
},
  "geometry": {"coordinates":[19.98016,60.30908],"type":"Point"}
}