{
  "type": "Feature",
  "properties": {
    "gn:admin1_code":"212",
    "gn:admin2_code":"43.0",
    "gn:asciiname":"Bonaes",
    "gn:country_code":"AX",
    "gn:dem":1,
    "gn:feature_class":"P",
    "gn:feature_code":"PPL",
    "gn:name":"Bon\u00e4s",
    "gn:population":0,
    "gn:timezone":"Europe/Mariehamn",
    "iso:country":"AX",
    "wof:name":"Bonaes",
    "wof:placetype":"locality"
},
  "geometry": {"coordinates":[19.59694,60.17778000000001],"type":"Point"}
}