{
  "type": "Feature",
  "properties": {
    "gn:admin1_code":"212",
    "gn:admin2_code":"736.0",
    "gn:asciiname":"Rangsby",
    "gn:country_code":"AX",
    "gn:dem":13,
    "gn:feature_class":"P",
    "gn:feature_code":"PPL",
    "gn:name":"Rangsby",
    "gn:population":0,
    "gn:timezone":"Europe/Mariehamn",
    "iso:country":"AX",
    "wof:name":"Rangsby",
    "wof:placetype":"locality"
},
  "geometry": {"coordinates":[20.075,60.27806],"type":"Point"}
}