{
  "type": "Feature",
  "properties": {
    "gn:admin1_code":"213",
    "gn:admin2_code":"941.0",
    "gn:asciiname":"Signedal",
    "gn:country_code":"AX",
    "gn:dem":14,
    "gn:feature_class":"P",
    "gn:feature_code":"PPL",
    "gn:name":"Signedal",
    "gn:population":0,
    "gn:timezone":"Europe/Mariehamn",
    "iso:country":"AX",
    "wof:name":"Signedal",
    "wof:placetype":"locality"
},
  "geometry": {"coordinates":[20.38306,60.22389],"type":"Point"}
}