{
  "type": "Feature",
  "properties": {
    "gn:admin1_code":"211",
    "gn:admin2_code":"478.0",
    "gn:asciiname":"Vaestra Ytternaes",
    "gn:country_code":"AX",
    "gn:dem":-9999,
    "gn:feature_class":"P",
    "gn:feature_code":"PPL",
    "gn:name":"V\u00e4stra Yttern\u00e4s",
    "gn:population":0,
    "gn:timezone":"Europe/Mariehamn",
    "iso:country":"AX",
    "wof:name":"Vaestra Ytternaes",
    "wof:placetype":"locality"
},
  "geometry": {"coordinates":[19.9375,60.07944000000001],"type":"Point"}
}