{
  "type": "Feature",
  "properties": {
    "gn:admin1_code":"213",
    "gn:admin2_code":"295.0",
    "gn:asciiname":"Kvarnkulla",
    "gn:country_code":"AX",
    "gn:dem":6,
    "gn:feature_class":"P",
    "gn:feature_code":"PPL",
    "gn:name":"Kvarnkulla",
    "gn:population":0,
    "gn:timezone":"Europe/Mariehamn",
    "iso:country":"AX",
    "wof:name":"Kvarnkulla",
    "wof:placetype":"locality"
},
  "geometry": {"coordinates":[20.765,60.26667],"type":"Point"}
}