{
  "type": "Feature",
  "properties": {
    "gn:gn_country":"AX",
    "gn:gn_fcode":"PPL",
    "gn:gn_pop":0,
    "iso:country":"AX",
    "name:unk_x_variant":[
        "Stalsvy"
    ],
    "qs_pg:aaroncc":"AX",
    "qs_pg:gn_country":"AX",
    "qs_pg:gn_fcode":"PPL",
    "qs_pg:gn_pop":0,
    "qs_pg:name":"St\u00e5lsby",
    "qs_pg:name_adm0":"\u00c5land",
    "qs_pg:name_adm1":"Finstr\u00f6m",
    "qs_pg:photos":116,
    "qs_pg:photos_1k":24,
    "qs_pg:photos_9k":1,
    "qs_pg:photos_9r":3,
    "qs_pg:photos_all":116,
    "qs_pg:photos_sr":3,
    "qs_pg:pop_sr":0,
    "qs_pg:qs_pg_placetype":"locality",
    "qs_pg:qs_pg_placetype_gp":"Town",
    "qs_pg:woe_adm0":12577865,
    "woe:adm0_id":12577865,
    "woe:name_adm0":"\u00c5land",
    "woe:name_adm1":"Finstr\u00f6m",
    "woe:placetype":"Town",
    "wof:name":"St\u00e5lsby",
    "wof:placetype":"locality"
},
  "geometry": {"coordinates":[19.98333,60.35],"type":"Point"}
}