{
  "type": "Feature",
  "properties": {
    "gn:admin1_code":"212",
    "gn:admin2_code":"76.0",
    "gn:asciiname":"Haellesby Sand",
    "gn:country_code":"AX",
    "gn:dem":-9999,
    "gn:feature_class":"P",
    "gn:feature_code":"PPL",
    "gn:name":"H\u00e4llesby Sand",
    "gn:population":0,
    "gn:timezone":"Europe/Mariehamn",
    "iso:country":"AX",
    "wof:name":"Haellesby Sand",
    "wof:placetype":"locality"
},
  "geometry": {"coordinates":[19.6975,60.18833000000001],"type":"Point"}
}