{
  "type": "Feature",
  "properties": {
    "gn:admin1_code":"212",
    "gn:admin2_code":"76.0",
    "gn:asciiname":"OEvergard",
    "gn:country_code":"AX",
    "gn:dem":7,
    "gn:feature_class":"P",
    "gn:feature_code":"PPL",
    "gn:name":"\u00d6verg\u00e5rd",
    "gn:population":0,
    "gn:timezone":"Europe/Mariehamn",
    "iso:country":"AX",
    "wof:name":"OEvergard",
    "wof:placetype":"locality"
},
  "geometry": {"coordinates":[19.75778,60.1875],"type":"Point"}
}