{
  "type": "Feature",
  "properties": {
    "gn:admin1_code":"212",
    "gn:admin2_code":"170.0",
    "gn:asciiname":"Kihla",
    "gn:country_code":"AX",
    "gn:dem":14,
    "gn:feature_class":"P",
    "gn:feature_code":"PPL",
    "gn:name":"Kihla",
    "gn:population":0,
    "gn:timezone":"Europe/Mariehamn",
    "iso:country":"AX",
    "wof:name":"Kihla",
    "wof:placetype":"locality"
},
  "geometry": {"coordinates":[19.98389,60.15833000000001],"type":"Point"}
}