{
  "type": "Feature",
  "properties": {
    "gn:admin1_code":"212",
    "gn:admin2_code":"60.0",
    "gn:asciiname":"Stornaes",
    "gn:country_code":"AX",
    "gn:dem":-9999,
    "gn:feature_class":"P",
    "gn:feature_code":"PPL",
    "gn:name":"Storn\u00e4s",
    "gn:population":0,
    "gn:timezone":"Europe/Mariehamn",
    "iso:country":"AX",
    "wof:name":"Stornaes",
    "wof:placetype":"locality"
},
  "geometry": {"coordinates":[19.94722,60.22333],"type":"Point"}
}