{
  "type": "Feature",
  "properties": {
    "gn:admin1_code":"213",
    "gn:admin2_code":"35.0",
    "gn:asciiname":"Lappo",
    "gn:country_code":"AX",
    "gn:dem":12,
    "gn:feature_class":"P",
    "gn:feature_code":"PPL",
    "gn:name":"Lappo",
    "gn:population":0,
    "gn:timezone":"Europe/Mariehamn",
    "iso:country":"AX",
    "name:und_x_variant":[
        "Lappoby-\u00c5land",
        "Lappaby",
        "Lappo"
    ],
    "wof:name":"Lappo",
    "wof:placetype":"locality"
},
  "geometry": {"coordinates":[20.98333,60.31667],"type":"Point"}
}