{
  "type": "Feature",
  "properties": {
    "gn:admin1_code":"212",
    "gn:admin2_code":"43.0",
    "gn:asciiname":"OEstra Mangsjoe",
    "gn:country_code":"AX",
    "gn:dem":2,
    "gn:feature_class":"P",
    "gn:feature_code":"PPL",
    "gn:name":"\u00d6stra Mangsj\u00f6",
    "gn:population":0,
    "gn:timezone":"Europe/Mariehamn",
    "iso:country":"AX",
    "wof:name":"OEstra Mangsjoe",
    "wof:placetype":"locality"
},
  "geometry": {"coordinates":[19.59361,60.18833000000001],"type":"Point"}
}