{
  "type": "Feature",
  "properties": {
    "gn:admin1_code":"212",
    "gn:admin2_code":"438.0",
    "gn:asciiname":"Norrgard",
    "gn:country_code":"AX",
    "gn:dem":11,
    "gn:feature_class":"P",
    "gn:feature_code":"PPL",
    "gn:name":"Norrg\u00e5rd",
    "gn:population":0,
    "gn:timezone":"Europe/Mariehamn",
    "iso:country":"AX",
    "wof:name":"Norrgard",
    "wof:placetype":"locality"
},
  "geometry": {"coordinates":[20.26361,60.08472],"type":"Point"}
}