{
  "type": "Feature",
  "properties": {
    "gn:admin1_code":"212",
    "gn:admin2_code":"170.0",
    "gn:asciiname":"Janses",
    "gn:country_code":"AX",
    "gn:dem":12,
    "gn:feature_class":"P",
    "gn:feature_code":"PPL",
    "gn:name":"Janses",
    "gn:population":0,
    "gn:timezone":"Europe/Mariehamn",
    "iso:country":"AX",
    "wof:name":"Janses",
    "wof:placetype":"locality"
},
  "geometry": {"coordinates":[20.00778,60.12444],"type":"Point"}
}