{
  "type": "Feature",
  "properties": {
    "gn:admin1_code":"212",
    "gn:admin2_code":"771.0",
    "gn:asciiname":"Naestgard",
    "gn:country_code":"AX",
    "gn:dem":10,
    "gn:feature_class":"P",
    "gn:feature_code":"PPL",
    "gn:name":"N\u00e4stg\u00e5rd",
    "gn:population":0,
    "gn:timezone":"Europe/Mariehamn",
    "iso:country":"AX",
    "wof:name":"Naestgard",
    "wof:placetype":"locality"
},
  "geometry": {"coordinates":[20.15583,60.19611],"type":"Point"}
}