{
  "type": "Feature",
  "properties": {
    "gn:admin1_code":"212",
    "gn:admin2_code":"417.0",
    "gn:asciiname":"Bengtsboele",
    "gn:country_code":"AX",
    "gn:dem":22,
    "gn:feature_class":"P",
    "gn:feature_code":"PPL",
    "gn:name":"Bengtsb\u00f6le",
    "gn:population":0,
    "gn:timezone":"Europe/Mariehamn",
    "iso:country":"AX",
    "wof:name":"Bengtsboele",
    "wof:placetype":"locality"
},
  "geometry": {"coordinates":[20.11272,60.06778000000001],"type":"Point"}
}