{
  "type": "Feature",
  "properties": {
    "gn:admin1_code":"212",
    "gn:admin2_code":"736.0",
    "gn:asciiname":"Stroemma",
    "gn:country_code":"AX",
    "gn:dem":46,
    "gn:feature_class":"P",
    "gn:feature_code":"PPL",
    "gn:name":"Str\u00f6mma",
    "gn:population":0,
    "gn:timezone":"Europe/Mariehamn",
    "iso:country":"AX",
    "wof:name":"Stroemma",
    "wof:placetype":"locality"
},
  "geometry": {"coordinates":[20.05,60.33333],"type":"Point"}
}