{
  "type": "Feature",
  "properties": {
    "gn:admin1_code":"212",
    "gn:admin2_code":"76.0",
    "gn:asciiname":"Vaestergard",
    "gn:country_code":"AX",
    "gn:dem":18,
    "gn:feature_class":"P",
    "gn:feature_code":"PPL",
    "gn:name":"V\u00e4sterg\u00e5rd",
    "gn:population":0,
    "gn:timezone":"Europe/Mariehamn",
    "iso:country":"AX",
    "wof:name":"Vaestergard",
    "wof:placetype":"locality"
},
  "geometry": {"coordinates":[19.75639,60.15889],"type":"Point"}
}