{
  "type": "Feature",
  "properties": {
    "gn:admin1_code":"212",
    "gn:admin2_code":"60.0",
    "gn:asciiname":"Roennhem",
    "gn:country_code":"AX",
    "gn:dem":5,
    "gn:feature_class":"P",
    "gn:feature_code":"PPL",
    "gn:name":"R\u00f6nnhem",
    "gn:population":0,
    "gn:timezone":"Europe/Mariehamn",
    "iso:country":"AX",
    "wof:name":"Roennhem",
    "wof:placetype":"locality"
},
  "geometry": {"coordinates":[19.89778,60.21444],"type":"Point"}
}