{
  "type": "Feature",
  "properties": {
    "gn:admin1_code":"212",
    "gn:admin2_code":"170.0",
    "gn:asciiname":"Brandoe",
    "gn:country_code":"AX",
    "gn:dem":1,
    "gn:feature_class":"P",
    "gn:feature_code":"PPL",
    "gn:name":"Brand\u00f6",
    "gn:population":0,
    "gn:timezone":"Europe/Mariehamn",
    "iso:country":"AX",
    "wof:name":"Brandoe",
    "wof:placetype":"locality"
},
  "geometry": {"coordinates":[19.88028,60.11417],"type":"Point"}
}