{
  "type": "Feature",
  "properties": {
    "gn:admin1_code":"212",
    "gn:admin2_code":"170.0",
    "gn:asciiname":"OEverby",
    "gn:country_code":"AX",
    "gn:dem":40,
    "gn:feature_class":"P",
    "gn:feature_code":"PPL",
    "gn:name":"\u00d6verby",
    "gn:population":0,
    "gn:timezone":"Europe/Mariehamn",
    "iso:country":"AX",
    "name:und_x_variant":[
        "Ofverby",
        "\u00d6verby"
    ],
    "wof:name":"OEverby",
    "wof:placetype":"locality"
},
  "geometry": {"coordinates":[19.98333,60.15],"type":"Point"}
}