{
  "type": "Feature",
  "properties": {
    "gn:admin1_code":"212",
    "gn:admin2_code":"417.0",
    "gn:asciiname":"Soedergard",
    "gn:country_code":"AX",
    "gn:dem":28,
    "gn:feature_class":"P",
    "gn:feature_code":"PPL",
    "gn:name":"S\u00f6derg\u00e5rd",
    "gn:population":0,
    "gn:timezone":"Europe/Mariehamn",
    "iso:country":"AX",
    "wof:name":"Soedergard",
    "wof:placetype":"locality"
},
  "geometry": {"coordinates":[20.01194,60.07722],"type":"Point"}
}